[
	{ "text": { "text": "2U, Inc. - twou", "type": "plain_text" }, "value": "twou - 0001459417" },
	{ "text": { "text": "3M CO - mmm", "type": "plain_text" }, "value": "mmm - 0000066740" },
	{ "text": { "text": "ADVANCED MICRO DEVICES INC - amd", "type": "plain_text" }, "value": "amd - 0000002488" },
	{ "text": { "text": "AT&T INC. - t", "type": "plain_text" }, "value": "t - 0000732717" },
	{ "text": { "text": "AbbVie Inc. - abbv", "type": "plain_text" }, "value": "abbv - 0001551152" },
	{ "text": { "text": "Activision Blizzard, Inc. - atvi", "type": "plain_text" }, "value": "atvi - 0000718877" },
	{ "text": { "text": "ADOBE INC. - adbe", "type": "plain_text" }, "value": "adbe - 0000796343" },
	{ "text": { "text": "Affirm Holdings, Inc. - afrm", "type": "plain_text" }, "value": "afrm - 0001820953" },
	{ "text": { "text": "Agora, Inc. - api", "type": "plain_text" }, "value": "api - 0001802883" },
	{ "text": { "text": "Airbnb, Inc. - abnb", "type": "plain_text" }, "value": "abnb - 0001559720" },
	{ "text": { "text": "ALBEMARLE CORP - alb", "type": "plain_text" }, "value": "alb - 0000915913" },
	{ "text": { "text": "Alibaba Group Holding Ltd - baba", "type": "plain_text" }, "value": "baba - 0001577552" },
	{ "text": { "text": "Alphabet Inc. - googl", "type": "plain_text" }, "value": "googl - 0001652044" },
	{ "text": { "text": "Alteryx, Inc. - ayx", "type": "plain_text" }, "value": "ayx - 0001689923" },
	{ "text": { "text": "AMAZON COM INC - amzn", "type": "plain_text" }, "value": "amzn - 0001018724" },
	{ "text": { "text": "American Airlines Group Inc. - aal", "type": "plain_text" }, "value": "aal - 0000006201" },
	{ "text": { "text": "AMERICAN EXPRESS CO - axp", "type": "plain_text" }, "value": "axp - 0000004962" },
	{ "text": { "text": "Apple Inc. - aapl", "type": "plain_text" }, "value": "aapl - 0000320193" },
	{ "text": { "text": "AquaBounty Technologies, Inc. - aqb", "type": "plain_text" }, "value": "aqb - 0001603978" },
	{ "text": { "text": "Arcimoto Inc - fuv", "type": "plain_text" }, "value": "fuv - 0001558583" },
	{ "text": { "text": "Arista Networks, Inc. - anet", "type": "plain_text" }, "value": "anet - 0001596532" },
	{ "text": { "text": "Asana, Inc. - asan", "type": "plain_text" }, "value": "asan - 0001477720" },
	{ "text": { "text": "Atlassian Corp Plc - team", "type": "plain_text" }, "value": "team - 0001650372" },
	{ "text": { "text": "AURORA CANNABIS INC - acb", "type": "plain_text" }, "value": "acb - 0001683541" },
	{ "text": { "text": "Autodesk, Inc. - adsk", "type": "plain_text" }, "value": "adsk - 0000769397" },
	{ "text": { "text": "AXON ENTERPRISE, INC. - axon", "type": "plain_text" }, "value": "axon - 0001069183" },
	{ "text": { "text": "Baidu, Inc. - bidu", "type": "plain_text" }, "value": "bidu - 0001329099" },
	{ "text": { "text": "BANK OF AMERICA CORP /DE/ - bac", "type": "plain_text" }, "value": "bac - 0000070858" },
	{ "text": { "text": "BEYOND MEAT, INC. - bynd", "type": "plain_text" }, "value": "bynd - 0001655210" },
	{ "text": { "text": "BigCommerce Holdings, Inc. - bigc", "type": "plain_text" }, "value": "bigc - 0001626450" },
	{ "text": { "text": "Bilibili Inc. - bili", "type": "plain_text" }, "value": "bili - 0001723690" },
	{ "text": { "text": "Bionano Genomics, Inc - bngo", "type": "plain_text" }, "value": "bngo - 0001411690" },
	{ "text": { "text": "BOEING CO - ba", "type": "plain_text" }, "value": "ba - 0000012927" },
	{ "text": { "text": "Booking Holdings Inc. - bkng", "type": "plain_text" }, "value": "bkng - 0001075531" },
	{ "text": { "text": "BOX INC - box", "type": "plain_text" }, "value": "box - 0001372612" },
	{ "text": { "text": "Broadcom Inc. - avgo", "type": "plain_text" }, "value": "avgo - 0001730168" },
	{ "text": { "text": "Bumble Inc. - bmbl", "type": "plain_text" }, "value": "bmbl - 0001830043" },
	{ "text": { "text": "C3.ai, Inc. - ai", "type": "plain_text" }, "value": "ai - 0001577526" },
	{ "text": { "text": "CRISPR Therapeutics AG - crsp", "type": "plain_text" }, "value": "crsp - 0001674416" },
	{ "text": { "text": "Canadian Solar Inc. - csiq", "type": "plain_text" }, "value": "csiq - 0001375877" },
	{ "text": { "text": "Canopy Growth Corp - cgc", "type": "plain_text" }, "value": "cgc - 0001737927" },
	{ "text": { "text": "CARNIVAL CORP - ccl", "type": "plain_text" }, "value": "ccl - 0000815097" },
	{ "text": { "text": "CARVANA CO. - cvna", "type": "plain_text" }, "value": "cvna - 0001690820" },
	{ "text": { "text": "Casper Sleep Inc. - cspr", "type": "plain_text" }, "value": "cspr - 0001598674" },
	{ "text": { "text": "CHEGG, INC - chgg", "type": "plain_text" }, "value": "chgg - 0001364954" },
	{ "text": { "text": "CHEVRON CORP - cvx", "type": "plain_text" }, "value": "cvx - 0000093410" },
	{ "text": { "text": "Chewy, Inc. - chwy", "type": "plain_text" }, "value": "chwy - 0001766502" },
	{ "text": { "text": "CHIPOTLE MEXICAN GRILL INC - cmg", "type": "plain_text" }, "value": "cmg - 0001058090" },
	{ "text": { "text": "CISCO SYSTEMS, INC. - csco", "type": "plain_text" }, "value": "csco - 0000858877" },
	{ "text": { "text": "Cloudflare, Inc. - net", "type": "plain_text" }, "value": "net - 0001477333" },
	{ "text": { "text": "CLOVER HEALTH INVESTMENTS, CORP. /DE - clov", "type": "plain_text" }, "value": "clov - 0001801170" },
	{ "text": { "text": "COCA COLA CO - ko", "type": "plain_text" }, "value": "ko - 0000021344" },
	{ "text": { "text": "Coinbase Global, Inc. - coin", "type": "plain_text" }, "value": "coin - 0001679788" },
	{ "text": { "text": "Corsair Gaming, Inc. - crsr", "type": "plain_text" }, "value": "crsr - 0001743759" },
	{ "text": { "text": "COSTCO WHOLESALE CORP /NEW - cost", "type": "plain_text" }, "value": "cost - 0000909832" },
	{ "text": { "text": "Coupa Software Inc - coup", "type": "plain_text" }, "value": "coup - 0001385867" },
	{ "text": { "text": "CrowdStrike Holdings, Inc. - crwd", "type": "plain_text" }, "value": "crwd - 0001535527" },
	{ "text": { "text": "Datadog, Inc. - ddog", "type": "plain_text" }, "value": "ddog - 0001561550" },
	{ "text": { "text": "DELTA AIR LINES, INC. - dal", "type": "plain_text" }, "value": "dal - 0000027904" },
	{ "text": { "text": "Digital Turbine, Inc. - apps", "type": "plain_text" }, "value": "apps - 0000317788" },
	{ "text": { "text": "Walt Disney Co - dis", "type": "plain_text" }, "value": "dis - 0001744489" },
	{ "text": { "text": "DOCUSIGN, INC. - docu", "type": "plain_text" }, "value": "docu - 0001261333" },
	{ "text": { "text": "DoorDash, Inc. - dash", "type": "plain_text" }, "value": "dash - 0001792789" },
	{ "text": { "text": "DraftKings Inc. - dkng", "type": "plain_text" }, "value": "dkng - 0001772757" },
	{ "text": { "text": "DROPBOX, INC. - dbx", "type": "plain_text" }, "value": "dbx - 0001467623" },
	{ "text": { "text": "Editas Medicine, Inc. - edit", "type": "plain_text" }, "value": "edit - 0001650664" },
	{ "text": { "text": "Elastic N.V. - estc", "type": "plain_text" }, "value": "estc - 0001707753" },
	{ "text": { "text": "ELECTRONIC ARTS INC. - ea", "type": "plain_text" }, "value": "ea - 0000712515" },
	{ "text": { "text": "Enphase Energy, Inc. - enph", "type": "plain_text" }, "value": "enph - 0001463101" },
	{ "text": { "text": "ETSY INC - etsy", "type": "plain_text" }, "value": "etsy - 0001370637" },
	{ "text": { "text": "EXXON MOBIL CORP - xom", "type": "plain_text" }, "value": "xom - 0000034088" },
	{ "text": { "text": "Facebook Inc - fb", "type": "plain_text" }, "value": "fb - 0001326801" },
	{ "text": { "text": "Farfetch Ltd - ftch", "type": "plain_text" }, "value": "ftch - 0001740915" },
	{ "text": { "text": "Fastly, Inc. - fsly", "type": "plain_text" }, "value": "fsly - 0001517413" },
	{ "text": { "text": "FEDEX CORP - fdx", "type": "plain_text" }, "value": "fdx - 0001048911" },
	{ "text": { "text": "FIRST SOLAR, INC. - fslr", "type": "plain_text" }, "value": "fslr - 0001274494" },
	{ "text": { "text": "Fiverr International Ltd. - fvrr", "type": "plain_text" }, "value": "fvrr - 0001762301" },
	{ "text": { "text": "FORD MOTOR CO - f", "type": "plain_text" }, "value": "f - 0000037996" },
	{ "text": { "text": "GENERAL ELECTRIC CO - ge", "type": "plain_text" }, "value": "ge - 0000040545" },
	{ "text": { "text": "General Motors Co - gm", "type": "plain_text" }, "value": "gm - 0001467858" },
	{ "text": { "text": "GoPro, Inc. - gpro", "type": "plain_text" }, "value": "gpro - 0001500435" },
	{ "text": { "text": "HUYA Inc. - huya", "type": "plain_text" }, "value": "huya - 0001728190" },
	{ "text": { "text": "Hilton Worldwide Holdings Inc. - hlt", "type": "plain_text" }, "value": "hlt - 0001585689" },
	{ "text": { "text": "INTERNATIONAL BUSINESS MACHINES CORP - ibm", "type": "plain_text" }, "value": "ibm - 0000051143" },
	{ "text": { "text": "IPG PHOTONICS CORP - ipgp", "type": "plain_text" }, "value": "ipgp - 0001111928" },
	{ "text": { "text": "ILLUMINA, INC. - ilmn", "type": "plain_text" }, "value": "ilmn - 0001110803" },
	{ "text": { "text": "INTEL CORP - intc", "type": "plain_text" }, "value": "intc - 0000050863" },
	{ "text": { "text": "Intellia Therapeutics, Inc. - ntla", "type": "plain_text" }, "value": "ntla - 0001652130" },
	{ "text": { "text": "INTUIT INC - intu", "type": "plain_text" }, "value": "intu - 0000896878" },
	{ "text": { "text": "INTUITIVE SURGICAL INC - isrg", "type": "plain_text" }, "value": "isrg - 0001035267" },
	{ "text": { "text": "Invitae Corp - nvta", "type": "plain_text" }, "value": "nvta - 0001501134" },
	{ "text": { "text": "Iridium Communications Inc. - irdm", "type": "plain_text" }, "value": "irdm - 0001418819" },
	{ "text": { "text": "JD.com, Inc. - jd", "type": "plain_text" }, "value": "jd - 0001549802" },
	{ "text": { "text": "JPMORGAN CHASE & CO - jpm", "type": "plain_text" }, "value": "jpm - 0000019617" },
	{ "text": { "text": "JOHNSON & JOHNSON - jnj", "type": "plain_text" }, "value": "jnj - 0000200406" },
	{ "text": { "text": "Jumia Technologies AG - jmia", "type": "plain_text" }, "value": "jmia - 0001756708" },
	{ "text": { "text": "Kraft Heinz Co - khc", "type": "plain_text" }, "value": "khc - 0001637459" },
	{ "text": { "text": "Lemonade, Inc. - lmnd", "type": "plain_text" }, "value": "lmnd - 0001691421" },
	{ "text": { "text": "LOCKHEED MARTIN CORP -  lmt", "type": "plain_text" }, "value": " lmt - 0000936468" },
	{ "text": { "text": "LOGITECH INTERNATIONAL S.A. - logi", "type": "plain_text" }, "value": "logi - 0001032975" },
	{ "text": { "text": "lululemon athletica inc. - lulu", "type": "plain_text" }, "value": "lulu - 0001397187" },
	{ "text": { "text": "Lyft, Inc. - lyft", "type": "plain_text" }, "value": "lyft - 0001759509" },
	{ "text": { "text": "MP Materials Corp. / DE - mp", "type": "plain_text" }, "value": "mp - 0001801368" },
	{ "text": { "text": "Mastercard Inc - ma", "type": "plain_text" }, "value": "ma - 0001141391" },
	{ "text": { "text": "Match Group, Inc. - mtch", "type": "plain_text" }, "value": "mtch - 0000891103" },
	{ "text": { "text": "Maxar Technologies Inc. - maxr", "type": "plain_text" }, "value": "maxr - 0001121142" },
	{ "text": { "text": "MCDONALDS CORP - mcd", "type": "plain_text" }, "value": "mcd - 0000063908" },
	{ "text": { "text": "Medallia, Inc. - mdla", "type": "plain_text" }, "value": "mdla - 0001540184" },
	{ "text": { "text": "MERCADOLIBRE INC - meli", "type": "plain_text" }, "value": "meli - 0001099590" },
	{ "text": { "text": "MICROSTRATEGY Inc - mstr", "type": "plain_text" }, "value": "mstr - 0001050446" },
	{ "text": { "text": "MICRON TECHNOLOGY INC - mu", "type": "plain_text" }, "value": "mu - 0000723125" },
	{ "text": { "text": "MICROSOFT CORP - msft", "type": "plain_text" }, "value": "msft - 0000789019" },
	{ "text": { "text": "Moderna, Inc. - mrna", "type": "plain_text" }, "value": "mrna - 0001682852" },
	{ "text": { "text": "MongoDB, Inc. - mdb", "type": "plain_text" }, "value": "mdb - 0001441816" },
	{ "text": { "text": "Nano Dimension Ltd. - nndm", "type": "plain_text" }, "value": "nndm - 0001643303" },
	{ "text": { "text": "NETFLIX INC - nflx", "type": "plain_text" }, "value": "nflx - 0001065280" },
	{ "text": { "text": "NEXTERA ENERGY INC - nee", "type": "plain_text" }, "value": "nee - 0000753308" },
	{ "text": { "text": "NIKE, Inc. - nke", "type": "plain_text" }, "value": "nke - 0000320187" },
	{ "text": { "text": "NIO Inc. - nio", "type": "plain_text" }, "value": "nio - 0001736541" },
	{ "text": { "text": "Niu Technologies - niu", "type": "plain_text" }, "value": "niu - 0001744781" },
	{ "text": { "text": "Nutanix, Inc. - ntnx", "type": "plain_text" }, "value": "ntnx - 0001618732" },
	{ "text": { "text": "NVIDIA CORP - nvda", "type": "plain_text" }, "value": "nvda - 0001045810" },
	{ "text": { "text": "Okta, Inc. - okta", "type": "plain_text" }, "value": "okta - 0001660134" },
	{ "text": { "text": "Opendoor Technologies Inc. - open", "type": "plain_text" }, "value": "open - 0001801169" },
	{ "text": { "text": "ORACLE CORP - orcl", "type": "plain_text" }, "value": "orcl - 0001341439" },
	{ "text": { "text": "PACIFIC BIOSCIENCES OF CALIFORNIA, INC. - pacb", "type": "plain_text" }, "value": "pacb - 0001299130" },
	{ "text": { "text": "PagerDuty, Inc. - pd", "type": "plain_text" }, "value": "pd - 0001568100" },
	{ "text": { "text": "Palantir Technologies Inc. - pltr", "type": "plain_text" }, "value": "pltr - 0001321655" },
	{ "text": { "text": "PayPal Holdings, Inc. - pypl", "type": "plain_text" }, "value": "pypl - 0001633917" },
	{ "text": { "text": "Paycom Software, Inc. - payc", "type": "plain_text" }, "value": "payc - 0001590955" },
	{ "text": { "text": "PELOTON INTERACTIVE, INC. - pton", "type": "plain_text" }, "value": "pton - 0001639825" },
	{ "text": { "text": "PENN NATIONAL GAMING INC - penn", "type": "plain_text" }, "value": "penn - 0000921738" },
	{ "text": { "text": "PEPSICO INC - pep", "type": "plain_text" }, "value": "pep - 0000077476" },
	{ "text": { "text": "PFIZER INC - pfe", "type": "plain_text" }, "value": "pfe - 0000078003" },
	{ "text": { "text": "Pinduoduo Inc. - pdd", "type": "plain_text" }, "value": "pdd - 0001737806" },
	{ "text": { "text": "PINTEREST, INC. - pins", "type": "plain_text" }, "value": "pins - 0001506293" },
	{ "text": { "text": "PLUG POWER INC - plug", "type": "plain_text" }, "value": "plug - 0001093691" },
	{ "text": { "text": "PROCTER & GAMBLE Co - pg", "type": "plain_text" }, "value": "pg - 0000080424" },
	{ "text": { "text": "Proto Labs Inc - prlb", "type": "plain_text" }, "value": "prlb - 0001443669" },
	{ "text": { "text": "Pure Storage, Inc. - pstg", "type": "plain_text" }, "value": "pstg - 0001474432" },
	{ "text": { "text": "QUALCOMM INC/DE - qcom", "type": "plain_text" }, "value": "qcom - 0000804328" },
	{ "text": { "text": "Redfin Corp - rdfn", "type": "plain_text" }, "value": "rdfn - 0001382821" },
	{ "text": { "text": "Revolve Group, Inc. - rvlv", "type": "plain_text" }, "value": "rvlv - 0001746618" },
	{ "text": { "text": "Robinhood Markets, Inc. - hood", "type": "plain_text" }, "value": "hood - 0001783879" },
	{ "text": { "text": "Roblox Corp - rblx", "type": "plain_text" }, "value": "rblx - 0001315098" },
	{ "text": { "text": "Rocket Companies, Inc. - rkt", "type": "plain_text" }, "value": "rkt - 0001805284" },
	{ "text": { "text": "ROKU, INC - roku", "type": "plain_text" }, "value": "roku - 0001428439" },
	{ "text": { "text": "SAP SE - sap", "type": "plain_text" }, "value": "sap - 0001000184" },
	{ "text": { "text": "SALESFORCE.COM, INC. - crm", "type": "plain_text" }, "value": "crm - 0001108524" },
	{ "text": { "text": "Schrodinger, Inc. - sdgr", "type": "plain_text" }, "value": "sdgr - 0001490978" },
	{ "text": { "text": "Sea Ltd - se", "type": "plain_text" }, "value": "se - 0001703399" },
	{ "text": { "text": "ServiceNow, Inc. - now", "type": "plain_text" }, "value": "now - 0001373715" },
	{ "text": { "text": "Shake Shack Inc. - shak", "type": "plain_text" }, "value": "shak - 0001620533" },
	{ "text": { "text": "SHOPIFY INC. - shop", "type": "plain_text" }, "value": "shop - 0001594805" },
	{ "text": { "text": "Skillz Inc. - sklz", "type": "plain_text" }, "value": "sklz - 0001801661" },
	{ "text": { "text": "SKYWORKS SOLUTIONS, INC. - swks", "type": "plain_text" }, "value": "swks - 0000004127" },
	{ "text": { "text": "Slack Technologies, Inc. - work", "type": "plain_text" }, "value": "work - 0001764925" },
	{ "text": { "text": "Snap Inc - snap", "type": "plain_text" }, "value": "snap - 0001564408" },
	{ "text": { "text": "Snowflake Inc. - snow", "type": "plain_text" }, "value": "snow - 0001640147" },
	{ "text": { "text": "SOLAREDGE TECHNOLOGIES, INC. - sedg", "type": "plain_text" }, "value": "sedg - 0001419612" },
	{ "text": { "text": "Sonos Inc - sono", "type": "plain_text" }, "value": "sono - 0001314727" },
	{ "text": { "text": "Sony Group Corp - sony", "type": "plain_text" }, "value": "sony - 0000313838" },
	{ "text": { "text": "SOUTHWEST AIRLINES CO - luv", "type": "plain_text" }, "value": "luv - 0000092380" },
	{ "text": { "text": "SPLUNK INC - splk", "type": "plain_text" }, "value": "splk - 0001353283" },
	{ "text": { "text": "Spotify Technology S.A. - spot", "type": "plain_text" }, "value": "spot - 0001639920" },
	{ "text": { "text": "Square, Inc. - sq", "type": "plain_text" }, "value": "sq - 0001512673" },
	{ "text": { "text": "Squarespace, Inc. - sqsp", "type": "plain_text" }, "value": "sqsp - 0001496963" },
	{ "text": { "text": "STAMPS.COM INC - stmp", "type": "plain_text" }, "value": "stmp - 0001082923" },
	{ "text": { "text": "STARBUCKS CORP - sbux", "type": "plain_text" }, "value": "sbux - 0000829224" },
	{ "text": { "text": "Stitch Fix, Inc. - sfix", "type": "plain_text" }, "value": "sfix - 0001576942" },
	{ "text": { "text": "STRATASYS LTD. - ssys", "type": "plain_text" }, "value": "ssys - 0001517396" },
	{ "text": { "text": "SUNPOWER CORP - spwr", "type": "plain_text" }, "value": "spwr - 0000867773" },
	{ "text": { "text": "Sunrun Inc. - run", "type": "plain_text" }, "value": "run - 0001469367" },
	{ "text": { "text": "Switch, Inc. - swch", "type": "plain_text" }, "value": "swch - 0001710583" },
	{ "text": { "text": "T-Mobile US, Inc. - tmus", "type": "plain_text" }, "value": "tmus - 0001283699" },
	{ "text": { "text": "TAIWAN SEMICONDUCTOR MANUFACTURING CO LTD - tsm", "type": "plain_text" }, "value": "tsm - 0001046179" },
	{ "text": { "text": "TAKE TWO INTERACTIVE SOFTWARE INC - ttwo", "type": "plain_text" }, "value": "ttwo - 0000946581" },
	{ "text": { "text": "TARGET CORP - tgt", "type": "plain_text" }, "value": "tgt - 0000027419" },
	{ "text": { "text": "Tattooed Chef, Inc. - ttcf", "type": "plain_text" }, "value": "ttcf - 0001741231" },
	{ "text": { "text": "Teladoc Health, Inc. - tdoc", "type": "plain_text" }, "value": "tdoc - 0001477449" },
	{ "text": { "text": "Tencent Holdings Ltd - tcehy", "type": "plain_text" }, "value": "tcehy - 0001293451" },
	{ "text": { "text": "TERADYNE, INC - ter", "type": "plain_text" }, "value": "ter - 0000097210" },
	{ "text": { "text": "Tesla, Inc. - tsla", "type": "plain_text" }, "value": "tsla - 0001318605" },
	{ "text": { "text": "Trade Desk, Inc. - ttd", "type": "plain_text" }, "value": "ttd - 0001671933" },
	{ "text": { "text": "Tilray, Inc. - tlry", "type": "plain_text" }, "value": "tlry - 0001731348" },
	{ "text": { "text": "TOYOTA MOTOR CORP/ - tm", "type": "plain_text" }, "value": "tm - 0001094517" },
	{ "text": { "text": "TWILIO INC - twlo", "type": "plain_text" }, "value": "twlo - 0001447669" },
	{ "text": { "text": "Twist Bioscience Corp - twst", "type": "plain_text" }, "value": "twst - 0001581280" },
	{ "text": { "text": "TWITTER, INC. - twtr", "type": "plain_text" }, "value": "twtr - 0001418091" },
	{ "text": { "text": "Uber Technologies, Inc - uber", "type": "plain_text" }, "value": "uber - 0001543151" },
	{ "text": { "text": "Unity Software Inc. - u", "type": "plain_text" }, "value": "u - 0001810806" },
	{ "text": { "text": "Upstart Holdings, Inc. - upst", "type": "plain_text" }, "value": "upst - 0001647639" },
	{ "text": { "text": "UPWORK, INC - upwk", "type": "plain_text" }, "value": "upwk - 0001627475" },
	{ "text": { "text": "VEEVA SYSTEMS INC - veev", "type": "plain_text" }, "value": "veev - 0001393052" },
	{ "text": { "text": "VERIZON COMMUNICATIONS INC - vz", "type": "plain_text" }, "value": "vz - 0000732712" },
	{ "text": { "text": "Virgin Galactic Holdings, Inc - spce", "type": "plain_text" }, "value": "spce - 0001706946" },
	{ "text": { "text": "VISA INC. -  v", "type": "plain_text" }, "value": " v - 0001403161" },
	{ "text": { "text": "Walmart Inc. - wmt", "type": "plain_text" }, "value": "wmt - 0000104169" },
	{ "text": { "text": "Wayfair Inc. - w", "type": "plain_text" }, "value": "w - 0001616707" },
	{ "text": { "text": "WELLS FARGO & COMPANY/MN - wfc", "type": "plain_text" }, "value": "wfc - 0000072971" },
	{ "text": { "text": "ContextLogic Inc. - wish", "type": "plain_text" }, "value": "wish - 0001822250" },
	{ "text": { "text": "Wix.com Ltd. - wix", "type": "plain_text" }, "value": "wix - 0001576789" },
	{ "text": { "text": "Workday, Inc. - wday", "type": "plain_text" }, "value": "wday - 0001327811" },
	{ "text": { "text": "Workhorse Group Inc. - wkhs", "type": "plain_text" }, "value": "wkhs - 0001425287" },
	{ "text": { "text": "XPENG INC. - xpev", "type": "plain_text" }, "value": "xpev - 0001810997" },
	{ "text": { "text": "Zendesk, Inc. - zen", "type": "plain_text" }, "value": "zen - 0001463172" },
	{ "text": { "text": "ZILLOW GROUP, INC. - z", "type": "plain_text" }, "value": "z - 0001617640" },
	{ "text": { "text": "Zoom Video Communications, Inc. - zm", "type": "plain_text" }, "value": "zm - 0001585521" },
	{ "text": { "text": "Zscaler, Inc. - zs", "type": "plain_text" }, "value": "zs - 0001713683" },
	{ "text": { "text": "EBAY INC - ebay", "type": "plain_text" }, "value": "ebay - 0001065088" },
	{ "text": { "text": "fuboTV Inc. /FL - fubo", "type": "plain_text" }, "value": "fubo - 0001484769" },
	{ "text": { "text": "IROBOT CORP - irbt", "type": "plain_text" }, "value": "irbt - 0001159167" }
]
