[{"text": {"text": "Nikola Corp - NKLA", "type": "plain_text"}, "value": "NKLA - 0001731289"}, {"text": {"text": "Opendoor Technologies Inc. - OPEN", "type": "plain_text"}, "value": "OPEN - 0001801169"}, {"text": {"text": "CLOVER HEALTH INVESTMENTS, CORP. /DE - CLOV", "type": "plain_text"}, "value": "CLOV - 0001801170"}, {"text": {"text": "Social Capital Hedosophia Holdings Corp. IV - IPOD", "type": "plain_text"}, "value": "IPOD - 0001818876"}, {"text": {"text": "Social Capital Hedosophia Holdings Corp. VI - IPOF", "type": "plain_text"}, "value": "IPOF - 0001818873"}, {"text": {"text": "SoFi Technologies, Inc. - SOFI", "type": "plain_text"}, "value": "SOFI - 0001818874"}, {"text": {"text": "Pershing Square Tontine Holdings, Ltd. - PSTH", "type": "plain_text"}, "value": "PSTH - 0001811882"}, {"text": {"text": "DraftKings Inc. - DKNG", "type": "plain_text"}, "value": "DKNG - 0001772757"}, {"text": {"text": "SoFi Technologies, Inc. - SOFI", "type": "plain_text"}, "value": "SOFI - 0001818874"}, {"text": {"text": "Social Capital Suvretta Holdings Corp. I - DNAA", "type": "plain_text"}, "value": "DNAA - 0001850266"}, {"text": {"text": "Social Capital Suvretta Holdings Corp. II - DNAB", "type": "plain_text"}, "value": "DNAB - 0001850271"}, {"text": {"text": "Social Capital Suvretta Holdings Corp. III - DNAC", "type": "plain_text"}, "value": "DNAC - 0001850270"}, {"text": {"text": "Social Capital Suvretta Holdings Corp. IV - DNAD", "type": "plain_text"}, "value": "DNAD - 0001850272"}]